Googlexcel_noPassword/Googlexcel_noPassword_v1.py
Googlexcel_noPassword/__init__.py
Googlexcel_noPassword-1.11.dist-info/LICENSE
Googlexcel_noPassword-1.11.dist-info/METADATA
Googlexcel_noPassword-1.11.dist-info/WHEEL
Googlexcel_noPassword-1.11.dist-info/top_level.txt
Googlexcel_noPassword-1.11.dist-info/RECORD
