Metadata-Version: 2.1
Name: Googlexcel-noPassword
Version: 1.11
Summary: Fetch all sheets of data from Google Spreadsheet Excel without auth/ password.
Home-page: https://www.linkedin.com/in/abhishek-venkatachalam-62121049/
Author: Abhishek Venkatachalam
Author-email: abhishek.venkatachalam06@gmail.com
License: UNKNOWN
Platform: UNKNOWN
Classifier: Programming Language :: Python :: 3
Classifier: License :: OSI Approved :: GNU General Public License v3 or later (GPLv3+)
Classifier: Operating System :: OS Independent
Requires-Python: >=3.7
License-File: LICENSE
